lib_test/__init__.py
lib_test/fn_test.py
lib_test_tanner-0.0.1.dist-info/METADATA
lib_test_tanner-0.0.1.dist-info/WHEEL
lib_test_tanner-0.0.1.dist-info/top_level.txt
lib_test_tanner-0.0.1.dist-info/RECORD
