Metadata-Version: 2.1
Name: lib-test-tanner
Version: 0.0.1
Summary: Librería para pruebas y funciones en Databricks
Home-page: https://github.com/nreyes-py/lib_test
Author: Nicolás Reyes Gallardo
Author-email: nreyes@inconsulting.cl
License: MIT
